robotframework_mbt-0.10.0.dist-info/licenses/LICENSE
robotmbt/__init__.py
robotmbt/modelspace.py
robotmbt/steparguments.py
robotmbt/substitutionmap.py
robotmbt/suitedata.py
robotmbt/suiteprocessors.py
robotmbt/suitereplacer.py
robotmbt/tracestate.py
robotmbt/version.py
robotframework_mbt-0.10.0.dist-info/METADATA
robotframework_mbt-0.10.0.dist-info/WHEEL
robotframework_mbt-0.10.0.dist-info/top_level.txt
robotframework_mbt-0.10.0.dist-info/RECORD
