Metadata-Version: 2.4
Name: robotframework-mbt
Version: 0.10.0
Summary: Model-Based Testing in Robot framework with test case generation
Author-email: Johan Foederer <github@famfoe.nl>
License: BSD 3-Clause License
Project-URL: Homepage, https://github.com/JFoederer/robotframeworkMBT
Keywords: robotframework,robot,mbt,bdd,testing
Classifier: License :: OSI Approved :: BSD License
Classifier: Programming Language :: Python :: 3
Classifier: Operating System :: OS Independent
Requires-Python: >=3.10
License-File: LICENSE
Requires-Dist: robotframework>=7.3
Dynamic: license-file
